RNWS/__init__.py
RNWS/cprint.py
RNWS/detect.py
RNWS/read.py
RNWS/timeit.py
RNWS/update.py
RNWS/write.py
RNWS/data/trading_date.csv
RNWS-0.2.1.dist-info/DESCRIPTION.rst
RNWS-0.2.1.dist-info/METADATA
RNWS-0.2.1.dist-info/RECORD
RNWS-0.2.1.dist-info/WHEEL
RNWS-0.2.1.dist-info/metadata.json
RNWS-0.2.1.dist-info/top_level.txt
