Metadata-Version: 2.0
Name: RNWS
Version: 0.2.1
Summary: read and write daily stock data
Home-page: UNKNOWN
Author: Yili Peng
Author-email: yili_peng@outlook.com
License: UNKNOWN
Platform: UNKNOWN
